MANIFEST.in
setup.py
FlaskSSL/__init__.py
FlaskSSL/_constants.py
FlaskSSL/_version.py
FlaskSSL.egg-info/PKG-INFO
FlaskSSL.egg-info/SOURCES.txt
FlaskSSL.egg-info/dependency_links.txt
FlaskSSL.egg-info/requires.txt
FlaskSSL.egg-info/top_level.txt
FlaskSSL/api/__init__.py
FlaskSSL/api/arguments.py
FlaskSSL/api/controllers.py
FlaskSSL/api/main.py
FlaskSSL/api/routes.py