Metadata-Version: 1.0
Name: FlaskSSL
Version: 1.0.0
Summary: SSL certification validation server.
Home-page: https://github.com/sfneal/flask-ssl-validation
Author: Stephen Neal
Author-email: stephen@stephenneal.net
License: UNKNOWN
Platform: UNKNOWN
